{
  "id": "2-stateSecrets",
  "title": "Госсекреты",
  "description": "<p>Тест на знание государственных секретов</p>",
  "questions": [
    {
      "type": "radio",
      "title": "Что такое государственные секреты?",
      "choices": [
        "информация общего доступа",
        "защищаемые государством сведения",
        "личные данные граждан",
        "коммерческая тайна"
      ],
      "correctAnswer": "защищаемые государством сведения"
    },
    {
      "type": "radio",
      "title": "Какие сведения могут быть отнесены к государственным секретам?",
      "choices": [
        "личные переписки граждан",
        "планы мобилизационной подготовки",
        "рецепты кулинарных блюд",
        "технологии производства игрушек"
      ],
      "correctAnswer": "планы мобилизационной подготовки"
    },
    {
      "type": "radio",
      "title": "Что понимается под информационной системой в защищенном исполнении?",
      "choices": [
        "любая компьютерная система",
        "информационная система ограниченного доступа для обработки секретной информации",
        "система для хранения общедоступной информации",
        "база данных предприятий"
      ],
      "correctAnswer": "информационная система ограниченного доступа для обработки секретной информации"
    },
    {
      "type": "radio",
      "title": "Кто отвечает за защиту государственных секретов в организации?",
      "choices": [
        "любой сотрудник",
        "руководитель организации",
        "секретарь",
        "бухгалтер"
      ],
      "correctAnswer": "руководитель организации"
    },
    {
      "type": "radio",
      "title": "Что означает гриф секретности?",
      "choices": [
        "название секретного документа",
        "реквизиты, свидетельствующие о степени секретности",
        "код доступа к секретной информации",
        "личный идентификатор сотрудника"
      ],
      "correctAnswer": "реквизиты, свидетельствующие о степени секретности"
    },
    {
      "type": "radio",
      "title": "Как определяется срок засекречивания сведений?",
      "choices": [
        "по усмотрению любого сотрудника",
        "в зависимости от степени секретности и необходимости защиты",
        "по решению иностранного государства",
        "в соответствии с пожеланиями граждан"
      ],
      "correctAnswer": "в зависимости от степени секретности и необходимости защиты"
    },
    {
      "type": "radio",
      "title": "Что не подлежит засекречиванию?",
      "choices": [
        "чрезвычайные ситуации и катастрофы",
        "планы обороны государства",
        "сведения о сотрудниках спецслужб",
        "разведывательная информация"
      ],
      "correctAnswer": "чрезвычайные ситуации и катастрофы"
    },
    {
      "type": "radio",
      "title": "Кто определяет единую политику в области защиты государственных секретов?",
      "choices": [
        "Министерство культуры",
        "Президент Республики Казахстан",
        "местные органы власти",
        "секретариат парламента"
      ],
      "correctAnswer": "Президент Республики Казахстан"
    },
    {
      "type": "radio",
      "title": "Что включает в себя допуск к государственным секретам?",
      "choices": [
        "процедуру оформления права на доступ к секретной информации",
        "уведомление граждан",
        "регистрацию коммерческих тайм",
        "публикацию данных в интернете"
      ],
      "correctAnswer": "процедуру оформления права на доступ к секретной информации"
    },
    {
      "type": "radio",
      "title": "Какие меры предусмотрены для защиты секретных сведений?",
      "choices": [
        "ликвидация секретных документов",
        "ограничение доступа и использование технических средств защиты",
        "публикация в открытых источниках",
        "регулярные пресс-конференции"
      ],
      "correctAnswer": "ограничение доступа и использование технических средств защиты"
    },
    {
      "type": "radio",
      "title": "Что означает рассекречивание сведений?",
      "choices": [
        "открытие доступа к ранее секретной информации",
        "уничтожение всех носителей информации",
        "публикация информации в интернете",
        "перевод информации на другой язык"
      ],
      "correctAnswer": "открытие доступа к ранее секретной информации"
    },
    {
      "type": "radio",
      "title": "Какой орган несет ответственность за контроль за исполнением системы защиты государственных секретов?",
      "choices": [
        "Министерство финансов",
        "Комитет национальной безопасности Республики Казахстан",
        "Министерство здравоохранения",
        "Акиматы"
      ],
      "correctAnswer": "Комитет национальной безопасности Республики Казахстан"
    },
    {
      "type": "radio",
      "title": "Что представляет собой государственная тайна?",
      "choices": [
        "планы маркетинговых исследований",
        "сведения, разглашение которых наносит ущерб национальной безопасности",
        "личные данные граждан",
        "экономические прогнозы"
      ],
      "correctAnswer": "сведения, разглашение которых наносит ущерб национальной безопасности"
    },
    {
      "type": "radio",
      "title": "Кто несет ответственность за организацию защиты секретных сведений в государственных органах?",
      "choices": [
        "любой сотрудник",
        "руководитель государственного органа",
        "граждане",
        "иностранные партнеры"
      ],
      "correctAnswer": "руководитель государственного органа"
    },
    {
      "type": "radio",
      "title": "Что включает в себя право собственности на государственные секреты?",
      "choices": [
        "право на продажу секретных сведений",
        "собственность Республики Казахстан на секретные сведения и их носители",
        "личное право граждан на секретные сведения",
        "право на изменение секретных сведений"
      ],
      "correctAnswer": "собственность Республики Казахстан на секретные сведения и их носители"
    },
    {
      "type": "radio",
      "title": "Что является объектом государственной тайны в области военной техники?",
      "choices": [
        "технологии производства игрушек",
        "разработка новых видов вооружения",
        "рецепты кулинарных блюд",
        "личные переписки граждан"
      ],
      "correctAnswer": "разработка новых видов вооружения"
    },
    {
      "type": "radio",
      "title": "Кто может проводить проверку граждан в связи с их допуском к государственным секретам?",
      "choices": [
        "Министерство культуры",
        "Комитет национальной безопасности Республики Казахстан",
        "местные органы власти",
        "коммерческие организации"
      ],
      "correctAnswer": "Комитет национальной безопасности Республики Казахстан"
    },
    {
      "type": "radio",
      "title": "Какое право имеют граждане в отношении засекречивания сведений?",
      "choices": [
        "право на публичное использование секретной информации",
        "право на обжалование обоснованности засекречивания сведений",
        "право на продажу секретной информации",
        "право на изменение секретной информации"
      ],
      "correctAnswer": "право на обжалование обоснованности засекречивания сведений"
    },
    {
      "type": "radio",
      "title": "Кто определяет перечень сведений, подлежащих засекречиванию?",
      "choices": [
        "Президент Республики Казахстан",
        "уполномоченные государственные органы",
        "местные органы власти",
        "коммерческие организации"
      ],
      "correctAnswer": "Президент Республики Казахстан"
    },
    {
      "type": "radio",
      "title": "Что включает в себя право на доступ к государственным секретам?",
      "choices": [
        "право на публикацию секретных данных",
        "санкционированное ознакомление со сведениями, составляющими государственные секреты",
        "право на изменение секретных данных",
        "право на коммерческое использование секретных данных"
      ],
      "correctAnswer": "санкционированное ознакомление со сведениями, составляющими государственные секреты"
    },
    {
      "type": "radio",
      "title": "Что является основанием для рассекречивания сведений?",
      "choices": [
        "изменение объема секретных данных",
        "окончание срока засекречивания",
        "публикация информации в интернете",
        "решение граждан"
      ],
      "correctAnswer": "окончание срока засекречивания"
    },
    {
      "type": "radio",
      "title": "Какие сведения не могут быть отнесены к государственным секретам?",
      "choices": [
        "планы обороны государства",
        "чрезвычайные ситуации и катастрофы",
        "разведывательная информация",
        "сведения о сотрудниках спецслужб"
      ],
      "correctAnswer": "чрезвычайные ситуации и катастрофы"
    },
    {
      "type": "radio",
      "title": "Кто определяет степень секретности сведений?",
      "choices": [
        "любой сотрудник организации",
        "руководители государственных органов",
        "иностранные партнеры",
        "граждане"
      ],
      "correctAnswer": "руководители государственных органов"
    },
    {
      "type": "radio",
      "title": "Какие действия считаются разглашением государственных секретов?",
      "choices": [
        "уничтожение секретной информации",
        "сообщение секретов лицам без права доступа",
        "перевод информации на другой язык",
        "личное использование информации"
      ],
      "correctAnswer": "сообщение секретов лицам без права доступа"
    },
    {
      "type": "radio",
      "title": "Какие сведения в области экономики относятся к государственным секретам?",
      "choices": [
        "прогнозы маркетинговых исследований",
        "планы государственного оборонного заказа",
        "рецепты кулинарных блюд",
        "личные переписки граждан"
      ],
      "correctAnswer": "планы государственного оборонного заказа"
    },
    {
      "type": "radio",
      "title": "Кто осуществляет лицензирование деятельности, связанной с государственными секретами?",
      "choices": [
        "Министерство финансов",
        "Комитет национальной безопасности Республики Казахстан",
        "Министерство культуры",
        "Акиматы"
      ],
      "correctAnswer": "Комитет национальной безопасности Республики Казахстан"
    },
    {
      "type": "radio",
      "title": "Какие сведения в области науки и техники относятся к государственным секретам?",
      "choices": [
        "планы маркетинговых исследований",
        "сведения о новейших достижениях, влияющих на обороноспособность",
        "рецепты кулинарных блюд",
        "личные переписки граждан"
      ],
      "correctAnswer": "сведения о новейших достижениях, влияющих на обороноспособность"
    },
    {
      "type": "radio",
      "title": "Что представляет собой служебная тайна?",
      "choices": [
        "сведения о планах маркетинговых исследований",
        "сведения, разглашение которых наносит ущерб интересам государства",
        "рецепты кулинарных блюд",
        "личные переписки граждан"
      ],
      "correctAnswer": "сведения, разглашение которых наносит ущерб интересам государства"
    },
    {
      "type": "radio",
      "title": "Какие сведения во внешнеэкономической области относятся к государственным секретам?",
      "choices": [
        "планы маркетинговых исследований",
        "сведения об экспорте и импорте вооружения",
        "рецепты кулинарных блюд",
        "личные переписки граждан"
      ],
      "correctAnswer": "сведения об экспорте и импорте вооружения"
    },
    {
      "type": "radio",
      "title": "Что такое информационная система в защищенном исполнении?",
      "choices": [
        "любая компьютерная система",
        "система для обработки секретной информации",
        "система для хранения общедоступной информации",
        "база данных предприятий"
      ],
      "correctAnswer": "система для обработки секретной информации"
    },
    {
      "type": "radio",
      "title": "Кто определяет перечень должностных лиц, наделенных полномочиями по отнесению сведений к государственным секретам?",
      "choices": [
        "Президент Республики Казахстан",
        "местные органы власти",
        "коммерческие организации",
        "граждане"
      ],
      "correctAnswer": "Президент Республики Казахстан"
    },
    {
      "type": "radio",
      "title": "Что является основанием для рассекречивания сведений?",
      "choices": [
        "изменение объема секретных данных",
        "окончание срока засекречивания",
        "публикация информации в интернете",
        "решение граждан"
      ],
      "correctAnswer": "окончание срока засекречивания"
    }
  ],
  "time": 10,
  "passingScore": 5,
  "questionsTotal": 10
}